Workbook

Sheet Реестр
A1: РЕЕСТР ЛОКАЛЬНЫХ РЕСУРСНЫХ ВЕДОМОСТЕЙ
A2: Объект: ПРИМЕР (условный). Цены IV кв. 2026г. г. Ташкент, сум
A4: № | B4: Марка РД | C4: Дисциплина | D4: Наименование ЛРВ | E4: Итого без НДС, сум | F4: НДС 12%, сум | G4: Материалы заказчика, сум | H4: Всего с НДС, сум | I4: Замечаний к РД | J4: Примечание
A5: 1 | B5: ТХ | C5: Технологические решения | D5: ЛРВ-ТХ | E5: ='ЛРВ-ТХ'!H45 -> 7.0606059e+08 | F5: ='ЛРВ-ТХ'!H46 -> 84727271 | G5: ='ЛРВ-ТХ'!H47 -> -27200000 | H5: ='ЛРВ-ТХ'!H48 -> 7.6358786e+08 | I5: =COUNTIF('ЛРВ-ТХ'!I:I,"⚠*") -> 1
A6: 2 | B6: ГП | C6: Генеральный план | D6: ЛРВ-ГП | E6: ='ЛРВ-ГП'!H25 -> 20630520 | F6: ='ЛРВ-ГП'!H26 -> 2475662.4 | G6: ='ЛРВ-ГП'!H27 -> 0 | H6: ='ЛРВ-ГП'!H28 -> 23106182 | I6: =COUNTIF('ЛРВ-ГП'!I:I,"⚠*") -> 0
C7: ИТОГО ПО ОБЪЕКТУ | E7: =SUM(E5:E6) -> 7.2669111e+08 | F7: =SUM(F5:F6) -> 87202933 | G7: =SUM(G5:G6) -> -27200000 | H7: =SUM(H5:H6) -> 7.8669405e+08 | I7: =SUM(I5:I6) -> 1
A9: ПРИМЕР: нормы — ШНК 4.02.01-04 (табл. 1-01-013), ШНК 4.02.25-07 (табл. 25-10-001); цены условные; дополнения к нормам в примере не проверялись.

Sheet Ресурсы
A1: Ключ | B1: тип | C1: Наименование материалов и конструкций | D1: Единица измерения | E1: единицы | F1: Источник цены | G1: Позиция в прайсе | H1: Ед. прайса | I1: Цена прайса, сум | J1: Коэф. пересчёта | K1: Способ сопоставления / основание | L1: Статус
A2: =C2&D2 -> ЗАТРАТЫ ТРУДА РАБОЧИХ-СТРОИТЕЛЕЙЧЕЛ-Ч | C2: ЗАТРАТЫ ТРУДА РАБОЧИХ-СТРОИТЕЛЕЙ | D2: ЧЕЛ-Ч | E2: =I2*J2 -> 45000 | F2: IV кв. 2026г. г. Ташкент | G2: Ставка рабочего-строителя | H2: ЧЕЛ-Ч | I2: 45000 | J2: 1 | K2: Совпадение наименования и ед. изм. | L2: Точно
A3: =C3&D3 -> ЗАТРАТЫ ТРУДА МАШИНИСТОВЧЕЛ-Ч | C3: ЗАТРАТЫ ТРУДА МАШИНИСТОВ | D3: ЧЕЛ-Ч | E3: =I3*J3 -> 0 | F3: По норме | G3: — | H3: ЧЕЛ-Ч | I3: 0 | J3: 1 | K3: Оплата машинистов учтена в стоимости маш-ч | L3: Точно
A4: =C4&D4 -> ДОП.ПЕРЕМЕЩЕНИЕ РАБОЧИХ-СТРОИТЕЛЕЙ ПО ТРАССЕ ДО МЕСТА РАБОТЫЧЕЛ-Ч | C4: ДОП.ПЕРЕМЕЩЕНИЕ РАБОЧИХ-СТРОИТЕЛЕЙ ПО ТРАССЕ ДО МЕСТА РАБОТЫ | D4: ЧЕЛ-Ч | E4: =I4*J4 -> 45000 | F4: IV кв. 2026г. г. Ташкент | G4: Ставка рабочего-строителя | H4: ЧЕЛ-Ч | I4: 45000 | J4: 1 | K4: По ставке рабочего-строителя | L4: Проверить
A5: =C5&D5 -> ДОП.ПЕРЕМЕЩЕНИЕ МАШИНИСТОВ ПО ТРАССЕ ДО МЕСТА РАБОТЫЧЕЛ-Ч | C5: ДОП.ПЕРЕМЕЩЕНИЕ МАШИНИСТОВ ПО ТРАССЕ ДО МЕСТА РАБОТЫ | D5: ЧЕЛ-Ч | E5: =I5*J5 -> 0 | F5: По норме | G5: — | H5: ЧЕЛ-Ч | I5: 0 | J5: 1 | K5: Как затраты труда машинистов | L5: Точно
A6: =C6&D6 -> ЭКСКАВАТОРЫ ОДНОКОВШОВЫЕ ДИЗЕЛЬНЫЕ НА ГУСЕНИЧНОМ ХОДУ ПРИ РАБОТЕ НА ДРУГИХ ВИДАХ СТРОИТЕЛЬСТВА (КРОМЕ ВОДОХОЗЯЙСТВЕННОГО) 0,65 М3МАШ-Ч | C6: ЭКСКАВАТОРЫ ОДНОКОВШОВЫЕ ДИЗЕЛЬНЫЕ НА ГУСЕНИЧНОМ ХОДУ ПРИ РАБОТЕ НА ДРУГИХ ВИДАХ СТРОИТЕЛЬСТВА (КРОМЕ ВОДОХОЗЯЙСТВЕННОГО) 0,65 М3 | D6: МАШ-Ч | E6: =I6*J6 -> 420000 | F6: IV кв. 2026г. г. Ташкент | G6: Экскаватор гусеничный 0,65 м3 | H6: МАШ-Ч | I6: 420000 | J6: 1 | K6: По смыслу (тип и ёмкость ковша совпадают) | L6: Проверить
A7: =C7&D7 -> БУЛЬДОЗЕРЫ ПРИ РАБОТЕ НА ДРУГИХ ВИДАХ СТРОИТЕЛЬСТВА (КРОМЕ ВОДОХОЗЯЙСТВЕННОГО) 79 (108) КВТ (Л.С.)МАШ-Ч | C7: БУЛЬДОЗЕРЫ ПРИ РАБОТЕ НА ДРУГИХ ВИДАХ СТРОИТЕЛЬСТВА (КРОМЕ ВОДОХОЗЯЙСТВЕННОГО) 79 (108) КВТ (Л.С.) | D7: МАШ-Ч | E7: =I7*J7 -> 380000 | F7: IV кв. 2026г. г. Ташкент | G7: Бульдозер 108 л.с. | H7: МАШ-Ч | I7: 380000 | J7: 1 | K7: По смыслу (мощность совпадает) | L7: Проверить
A8: =C8&D8 -> КРАНЫ-ТРУБОУКЛАДЧИКИ ГРУЗОПОДЪЕМНОСТЬЮ 12 ТМАШ-Ч | C8: КРАНЫ-ТРУБОУКЛАДЧИКИ ГРУЗОПОДЪЕМНОСТЬЮ 12 Т | D8: МАШ-Ч | E8: =I8*J8 -> 520000 | F8: IV кв. 2026г. г. Ташкент | G8: Трубоукладчик 12 т | H8: МАШ-Ч | I8: 520000 | J8: 1 | K8: По смыслу (грузоподъёмность совпадает) | L8: Проверить
A9: =C9&D9 -> ЗАХВАТ КЛЕЩЕВОЙ АВТОМАТИЧЕСКИЙ КЗ-531 ГРУЗОПОДЪЕМНОСТЬЮ 4 ТМАШ-Ч | C9: ЗАХВАТ КЛЕЩЕВОЙ АВТОМАТИЧЕСКИЙ КЗ-531 ГРУЗОПОДЪЕМНОСТЬЮ 4 Т | D9: МАШ-Ч | L9: Нет цены
A10: =C10&D10 -> АГРЕГАТЫ СВАРОЧНЫЕ ДВУХПОСТОВЫЕ ДЛЯ РУЧНОЙ СВАРКИ НА ТРАКТОРЕ 79 КВТ (108 Л.С.)МАШ-Ч | C10: АГРЕГАТЫ СВАРОЧНЫЕ ДВУХПОСТОВЫЕ ДЛЯ РУЧНОЙ СВАРКИ НА ТРАКТОРЕ 79 КВТ (108 Л.С.) | D10: МАШ-Ч | E10: =I10*J10 -> 160000 | F10: IV кв. 2026г. г. Ташкент | G10: Сварочный агрегат двухпостовой на тракторе | H10: МАШ-Ч | I10: 160000 | J10: 1 | K10: По смыслу | L10: Проверить
A11: =C11&D11 -> УСТАНОВКИ ГОРИЗОНТАЛЬНОГО БУРЕНИЯ ДЛЯ ТРУБ ДИАМЕТРОМ 325-630 МММАШ-Ч | C11: УСТАНОВКИ ГОРИЗОНТАЛЬНОГО БУРЕНИЯ ДЛЯ ТРУБ ДИАМЕТРОМ 325-630 ММ | D11: МАШ-Ч | E11: =I11*J11 -> 650000 | F11: IV кв. 2026г. г. Ташкент | G11: УГБ 325-630 | H11: МАШ-Ч | I11: 650000 | J11: 1 | K11: По смыслу | L11: Проверить
A12: =C12&D12 -> УСТАНОВКИ ДЛЯ ОТКРЫТОГО ВОДООТЛИВА НА БАЗЕ ТРАКТОРА 700 М3/ЧАСМАШ-Ч | C12: УСТАНОВКИ ДЛЯ ОТКРЫТОГО ВОДООТЛИВА НА БАЗЕ ТРАКТОРА 700 М3/ЧАС | D12: МАШ-Ч | E12: =I12*J12 -> 210000 | F12: IV кв. 2026г. г. Ташкент | G12: Водоотливная установка 700 м3/ч | H12: МАШ-Ч | I12: 210000 | J12: 1 | K12: По смыслу | L12: Проверить
A13: =C13&D13 -> СПЕЦАВТОМАШИНЫ, ГРУЗОДОПОДЪЕМНОСТЬ ДО 8 Т, ВЕЗДЕХОДМАШ-Ч | C13: СПЕЦАВТОМАШИНЫ, ГРУЗОДОПОДЪЕМНОСТЬ ДО 8 Т, ВЕЗДЕХОД | D13: МАШ-Ч | E13: =I13*J13 -> 300000 | F13: IV кв. 2026г. г. Ташкент | G13: Вездеход грузовой 8 т | H13: МАШ-Ч | I13: 300000 | J13: 1 | K13: По смыслу | L13: Проверить
A14: =C14&D14 -> МАШИНЫ ШЛИФОВАЛЬНЫЕ ЭЛЕКТРИЧЕСКИЕМАШ-Ч | C14: МАШИНЫ ШЛИФОВАЛЬНЫЕ ЭЛЕКТРИЧЕСКИЕ | D14: МАШ-Ч | E14: =I14*J14 -> 8000 | F14: IV кв. 2026г. г. Ташкент | G14: Машина шлифовальная электрическая | H14: МАШ-Ч | I14: 8000 | J14: 1 | K14: Совпадение наименования и ед. изм. | L14: Точно
A15: =C15&D15 -> ЩЕБЕНЬМ3 | C15: ЩЕБЕНЬ | D15: М3 | E15: =I15*J15 -> 203000 | F15: IV кв. 2026г. г. Ташкент | G15: Щебень фр. 20-40 | H15: Т | I15: 140000 | J15: 1.45 | K15: Пересчёт Т → М3: насыпная плотность 1,45 т/м3 | L15: Проверить
A16: =C16&D16 -> ТРУБЫ СТАЛЬНЫЕ ЭЛЕКТРОСВАРНЫЕ ПРЯМОШОВНЫЕ СО СНЯТОЙ ФАСКОЙ ДИАМЕТРОМ ОТ 20 ДО 377 ММ ИЗ СТАЛИ МАРОК БСТ2КП-БСТ4КП И БСТ2ПС-БСТ4ПС НАРУЖНЫЙ ДИАМЕТР 325 ММ ТОЛЩИНА СТЕНКИ 6 МММ | C16: ТРУБЫ СТАЛЬНЫЕ ЭЛЕКТРОСВАРНЫЕ ПРЯМОШОВНЫЕ СО СНЯТОЙ ФАСКОЙ ДИАМЕТРОМ ОТ 20 ДО 377 ММ ИЗ СТАЛИ МАРОК БСТ2КП-БСТ4КП И БСТ2ПС-БСТ4ПС НАРУЖНЫЙ ДИАМЕТР 325 ММ ТОЛЩИНА СТЕНКИ 6 ММ | D16: М | E16: =I16*J16 -> 519420 | F16: IV кв. 2026г. г. Ташкент | G16: Труба 325х6 | H16: Т | I16: 11000000 | J16: 0.04722 | K16: Пересчёт Т → М: 47,22 кг/м (ГОСТ 10704) | L16: Проверить
A17: =C17&D17 -> ТРУБЫ СТАЛЬНЫЕ ЭЛЕКТРОСВАРНЫЕ ПРЯМОШОВНЫЕ И СПИРАЛЬНО-ШОВНЫЕ БОЛЬШИХ ДИАМЕТРОВ ГРУППЫ А И Б С СОПРОТИВЛЕНИЕМ ПО РАЗРЫВУ 38 КГС/ММ2 НАРУЖНЫЙ ДИАМЕТР 530 ММ ТОЛЩИНА СТЕНКИ 8 МММ | C17: ТРУБЫ СТАЛЬНЫЕ ЭЛЕКТРОСВАРНЫЕ ПРЯМОШОВНЫЕ И СПИРАЛЬНО-ШОВНЫЕ БОЛЬШИХ ДИАМЕТРОВ ГРУППЫ А И Б С СОПРОТИВЛЕНИЕМ ПО РАЗРЫВУ 38 КГС/ММ2 НАРУЖНЫЙ ДИАМЕТР 530 ММ ТОЛЩИНА СТЕНКИ 8 ММ | D17: М | E17: =I17*J17 -> 1184500 | F17: IV кв. 2026г. г. Ташкент | G17: Труба 530х8 | H17: Т | I17: 11500000 | J17: 0.103 | K17: Пересчёт Т → М: 103,0 кг/м (ГОСТ 10704) | L17: Проверить
A18: =C18&D18 -> ЭЛЕКТРОДЫ С ОСНОВНЫМ ПОКРЫТИЕМ КЛАССА Э42А ДИАМЕТРОМ 2,5 ММТ | C18: ЭЛЕКТРОДЫ С ОСНОВНЫМ ПОКРЫТИЕМ КЛАССА Э42А ДИАМЕТРОМ 2,5 ММ | D18: Т | E18: =I18*J18 -> 16500000 | F18: IV кв. 2026г. г. Ташкент | G18: Электроды Э42А Ø2,5 | H18: КГ | I18: 16500 | J18: 1000 | K18: Пересчёт КГ → Т (×1000) | L18: Проверить
A19: =C19&D19 -> ЭЛЕКТРОДЫ С ОСНОВНЫМ ПОКРЫТИЕМ КЛАССА Э50А ДИАМЕТРОМ 4 ММТ | C19: ЭЛЕКТРОДЫ С ОСНОВНЫМ ПОКРЫТИЕМ КЛАССА Э50А ДИАМЕТРОМ 4 ММ | D19: Т | E19: =I19*J19 -> 15000000 | F19: IV кв. 2026г. г. Ташкент | G19: Электроды сварочные Э50А Ø4 | H19: Т | I19: 15000000 | J19: 1 | K19: По смыслу | L19: Проверить
A20: =C20&D20 -> ГРУНТОВКА ГТ-752Т | C20: ГРУНТОВКА ГТ-752 | D20: Т | E20: =I20*J20 -> 28000000 | F20: IV кв. 2026г. г. Ташкент | G20: Грунтовка ГТ-752 | H20: КГ | I20: 28000 | J20: 1000 | K20: Пересчёт КГ → Т (×1000) | L20: Проверить
A21: =C21&D21 -> ЛЕНТА ПОЛИВИНИЛХЛОРИДНАЯ ДЛЯ ИЗОЛЯЦИИ ГАЗОНЕФТЕПРО-ДУКТОПРОВОДОВ ПВХ-БК (ЛИПКАЯ), ТОЛЩИНОЙ 0.4 МММ2 | C21: ЛЕНТА ПОЛИВИНИЛХЛОРИДНАЯ ДЛЯ ИЗОЛЯЦИИ ГАЗОНЕФТЕПРО-ДУКТОПРОВОДОВ ПВХ-БК (ЛИПКАЯ), ТОЛЩИНОЙ 0.4 ММ | D21: М2 | E21: =I21*J21 -> 9500 | F21: IV кв. 2026г. г. Ташкент | G21: Лента ПВХ-БК 0,4 мм | H21: М2 | I21: 9500 | J21: 1 | K21: По смыслу | L21: Проверить
... A25: =C25&D25 -> ЩЕТКИ КОЛЬЦЕВЫЕ ПРОВОЛОЧНЫЕШТ | C25: ЩЕТКИ КОЛЬЦЕВЫЕ ПРОВОЛОЧНЫЕ | D25: ШТ | E25: =I25*J25 -> 35000 | F25: IV кв. 2026г. г. Ташкент | G25: Щётка кольцевая проволочная | H25: ШТ | I25: 35000 | J25: 1 | K25: Совпадение наименования и ед. изм. | L25: Точно
A26: =C26&D26 -> КРАН ШАРОВОЙ ДУ500 РУ8,0 МПА ПОДЗЕМНОЙ УСТАНОВКИШТ | B26: обор. | C26: КРАН ШАРОВОЙ ДУ500 РУ8,0 МПА ПОДЗЕМНОЙ УСТАНОВКИ | D26: ШТ | E26: =I26*J26 -> 185000000 | F26: IV кв. 2026г. г. Ташкент | G26: Кран шаровой Ду500 Ру80 | H26: ШТ | I26: 185000000 | J26: 1 | K26: Совпадение наименования и ед. изм. | L26: Точно
A27: =C27&D27 -> КАБЕЛЬ ВВГНГ(А)-LS 3Х2,5М | B27: каб. | C27: КАБЕЛЬ ВВГНГ(А)-LS 3Х2,5 | D27: М | E27: =I27*J27 -> 12500 | F27: IV кв. 2026г. г. Ташкент | G27: Кабель ВВГнг-LS 3х2,5 | H27: М | I27: 12500 | J27: 1 | K27: Совпадение наименования и ед. изм. | L27: Точно
A28: =C28&D28 -> ОТВОД ГНУТЫЙ 30° 530Х8ШТ | B28: мз | C28: ОТВОД ГНУТЫЙ 30° 530Х8 | D28: ШТ | E28: =I28*J28 -> 6800000 | F28: IV кв. 2026г. г. Ташкент | G28: Отвод гнутый 30° 530х8 | H28: ШТ | I28: 6800000 | J28: 1 | K28: Совпадение наименования и ед. изм. | L28: Точно
C30: E = Цена прайса × Коэф. пересчёта (I×J); нет цены — E пусто. Колонки G–L сгруппированы (кнопка «+»). Синим — данные прайса. Статус: зелёный — точно; жёлтый — по смыслу/с пересчётом, проверить; красный — нет цены.

Sheet Спецификация
A1: СПЕЦИФИКАЦИЯ ОБОРУДОВАНИЯ, ИЗДЕЛИЙ И МАТЕРИАЛОВ
A2: Объект: ПРИМЕР (условный). Источник: РД марки ТХ, ГП
A4: № | B4: Наименование и техническая характеристика | C4: Ед. изм. | D4: Кол-во | E4: Раздел | F4: Примечание
A5: ТХ — ТЕХНОЛОГИЧЕСКИЕ РЕШЕНИЯ
A6: Раздел 1. Оборудование
A7: 1 | B7: Кран шаровой Ду500 Ру8,0 МПа подземной установки | C7: шт | D7: 3 | E7: Оборудование (обор.) | F7: ⚠ Замечание № 1 к РД: в спецификации 2 шт, на листе ТХ-3 — 3 шт. Принято 3 шт (больший)
A8: Раздел 2. Материалы
A9: 2 | B9: Отвод гнутый 30° 530×8 | C9: шт | D9: 4 | E9: Материал заказчика (мз) | F9: Лист ТХ-4
A10: 3 | B10: Труба стальная электросварная 530×8 (кожух) | C10: м | D10: 30.3 | E10: Материал подрядчика | F10: Учтена в норме 25-10-001-05 (30,3 м на переход)
A11: Раздел 3. Кабельная продукция
A12: 4 | B12: Кабель ВВГнг(А)-LS 3×2,5 | C12: м | D12: 150 | E12: Кабель (каб.) | F12: Лист ТХ-6, к электроприводу крана
A13: ГП — ГЕНЕРАЛЬНЫЙ ПЛАН
A14: Раздел 1. Материалы
A15: 5 | B15: Щебень | C15: м3 | D15: 0.05 | E15: Материал подрядчика | F15: Учтён в норме 01-01-013-8

Sheet ВОР
A1: ВЕДОМОСТЬ ОБЪЁМОВ РАБОТ
A2: Объект: ПРИМЕР (условный)
A4: № | B4: Наименование работ | C4: Ед. изм. | D4: Кол-во | E4: Шифр норматива | F4: Примечание
A5: ТХ — ТЕХНОЛОГИЧЕСКИЕ РЕШЕНИЯ
A6: Раздел 1. Переходы трубопровода
A7: 1 | B7: Бестраншейная прокладка кожуха Ду 500 мм методом горизонтального бурения, L=30 м, группа грунтов 2 | C7: переход | D7: 1 | E7: 25-10-001-05 | F7: Лист ТХ-2 (профиль перехода), ведомость переходов ТХ-1
A8: Раздел 2. Монтаж оборудования
A9: 2 | B9: Монтаж кранов шаровых Ду500 подземной установки | C9: шт | D9: =Спецификация!D7 -> 3 | E9: норма не подобрана | F9: ⚠ Замечание № 1 к РД: спецификация 2 шт / лист ТХ-3 — 3 шт. Принято 3 шт (больший). Норму на монтаж подобрать по ШНК 4.17 (в примере не приводится)
A10: ГП — ГЕНЕРАЛЬНЫЙ ПЛАН
A11: Раздел 1. Земляные работы
A12: 3 | B12: Разработка грунта с погрузкой на автомобили-самосвалы экскаватором 0,65 м3, группа грунтов 2 | C12: м3 | D12: 1250 | E12: 01-01-013-8 | F12: Лист ГП-2 (ведомость объёмов земляных масс): 1 250 м3; по картограмме ГП-3 — 1 180 м3. Принято 1 250 м3 (больший)
A14: ОБЩИЕ ПРИМЕЧАНИЯ
A15: 1. Объёмы приняты по РД марок ТХ и ГП; при расхождении между листами принят больший объём.
A16: 2. Шифры норм — ШНК 4.02.01-04, ШНК 4.02.25-07 (репозиторий SHNK_GSN) с учётом дополнений № 1–15.
A17: 3. Строки, выделенные оранжевым, содержат замечания к РД — см. перечень ниже.
A19: ЗАМЕЧАНИЯ К РД
A20: № | B20: Замечание | C20: Лист РД | E20: Принято | F20: Статус
A21: 1 | B21: Кран шаровой Ду500: в спецификации 2 шт, на плане — 3 шт | C21: ТХ-3 | E21: 3 шт | F21: Направить проектировщику

Sheet ЛРВ-ТХ
A1: N п.п. | B1: Шифр номера нормативов и коды ресурсов | C1: Наименование работ и затрат | D1: Единица измерения | E1: Количество | G1: Стоимость | I1: Примечание
E2: на ед. изм. | F2: по проектным данным | G2: Стоимость за ед. | H2: СУММА
A3: 1 | B3: 2 | C3: 3 | D3: 4 | E3: 5 | F3: 6 | G3: 7 | H3: 8 | I3: 9
A4: РАЗДЕЛ 1. ПЕРЕХОДЫ ТРУБОПРОВОДА
A5: 1 | B5: 25-10-001-05 | C5: БЕСТРАНШЕЙНАЯ ПРОКЛАДКА КОЖУХОВ ДУ 500 ММ МЕТОДОМ ГОРИЗОНТАЛЬНОГО БУРЕНИЯ В ГРУНТАХ ЕСТЕСТВЕННОЙ ВЛАЖНОСТИ (ПРОТЯЖЕННОСТЬ ЗАКРЫТОЙ ПРОХОДКИ - 30 М), ГРУППА ГРУНТОВ 2 | D5: 1 ПЕРЕХОД | E5: =ВОР!D7 -> 1
A6: 1.1 | B6: 1 | C6: ЗАТРАТЫ ТРУДА РАБОЧИХ-СТРОИТЕЛЕЙ | D6: ЧЕЛ-Ч | E6: 79.93 | F6: =+E6*$E$5 -> 79.93 | G6: =+VLOOKUP(C6&D6,Ресурсы!A:E,5,0) -> 45000 | H6: =+F6*G6 -> 3596850
A7: 1.2 | B7: 2 | C7: ЗАТРАТЫ ТРУДА МАШИНИСТОВ | D7: ЧЕЛ-Ч | E7: 95.53 | F7: =+E7*$E$5 -> 95.53 | G7: =+VLOOKUP(C7&D7,Ресурсы!A:E,5,0) -> 0 | H7: =+F7*G7 -> 0
A8: 1.3 | B8: 2.1 | C8: ДОП.ПЕРЕМЕЩЕНИЕ РАБОЧИХ-СТРОИТЕЛЕЙ ПО ТРАССЕ ДО МЕСТА РАБОТЫ | D8: ЧЕЛ-Ч | E8: 9.99 | F8: =+E8*$E$5 -> 9.99 | G8: =+VLOOKUP(C8&D8,Ресурсы!A:E,5,0) -> 45000 | H8: =+F8*G8 -> 449550
A9: 1.4 | B9: 2.2 | C9: ДОП.ПЕРЕМЕЩЕНИЕ МАШИНИСТОВ ПО ТРАССЕ ДО МЕСТА РАБОТЫ | D9: ЧЕЛ-Ч | E9: 11.94 | F9: =+E9*$E$5 -> 11.94 | G9: =+VLOOKUP(C9&D9,Ресурсы!A:E,5,0) -> 0 | H9: =+F9*G9 -> 0
A10: 1.5 | B10: С 2724 | C10: КРАНЫ-ТРУБОУКЛАДЧИКИ ГРУЗОПОДЪЕМНОСТЬЮ 12 Т | D10: МАШ-Ч | E10: 30.52 | F10: =+E10*$E$5 -> 30.52 | G10: =+VLOOKUP(C10&D10,Ресурсы!A:E,5,0) -> 520000 | H10: =+F10*G10 -> 15870400
A11: 1.6 | B11: С 2932 | C11: ЗАХВАТ КЛЕЩЕВОЙ АВТОМАТИЧЕСКИЙ КЗ-531 ГРУЗОПОДЪЕМНОСТЬЮ 4 Т | D11: МАШ-Ч | E11: 2.16 | F11: =+E11*$E$5 -> 2.16 | G11: =+VLOOKUP(C11&D11,Ресурсы!A:E,5,0) -> 0 | H11: =+F11*G11 -> 0
A12: 1.7 | B12: С 126 | C12: АГРЕГАТЫ СВАРОЧНЫЕ ДВУХПОСТОВЫЕ ДЛЯ РУЧНОЙ СВАРКИ НА ТРАКТОРЕ 79 КВТ (108 Л.С.) | D12: МАШ-Ч | E12: 10.83 | F12: =+E12*$E$5 -> 10.83 | G12: =+VLOOKUP(C12&D12,Ресурсы!A:E,5,0) -> 160000 | H12: =+F12*G12 -> 1732800
A13: 1.8 | B13: С 2006 | C13: УСТАНОВКИ ГОРИЗОНТАЛЬНОГО БУРЕНИЯ ДЛЯ ТРУБ ДИАМЕТРОМ 325-630 ММ | D13: МАШ-Ч | E13: 19.82 | F13: =+E13*$E$5 -> 19.82 | G13: =+VLOOKUP(C13&D13,Ресурсы!A:E,5,0) -> 650000 | H13: =+F13*G13 -> 12883000
A14: 1.9 | B14: С 1957 | C14: УСТАНОВКИ ДЛЯ ОТКРЫТОГО ВОДООТЛИВА НА БАЗЕ ТРАКТОРА 700 М3/ЧАС | D14: МАШ-Ч | E14: 12.39 | F14: =+E14*$E$5 -> 12.39 | G14: =+VLOOKUP(C14&D14,Ресурсы!A:E,5,0) -> 210000 | H14: =+F14*G14 -> 2601900
A15: 1.10 | B15: С 1648 | C15: СПЕЦАВТОМАШИНЫ, ГРУЗОДОПОДЪЕМНОСТЬ ДО 8 Т, ВЕЗДЕХОД | D15: МАШ-Ч | E15: 21.97 | F15: =+E15*$E$5 -> 21.97 | G15: =+VLOOKUP(C15&D15,Ресурсы!A:E,5,0) -> 300000 | H15: =+F15*G15 -> 6591000
A16: 1.11 | B16: С 1147 | C16: МАШИНЫ ШЛИФОВАЛЬНЫЕ ЭЛЕКТРИЧЕСКИЕ | D16: МАШ-Ч | E16: 0.52 | F16: =+E16*$E$5 -> 0.52 | G16: =+VLOOKUP(C16&D16,Ресурсы!A:E,5,0) -> 8000 | H16: =+F16*G16 -> 4160
A17: 1.12 | B17: С 37202 | C17: ТРУБЫ СТАЛЬНЫЕ ЭЛЕКТРОСВАРНЫЕ ПРЯМОШОВНЫЕ СО СНЯТОЙ ФАСКОЙ ДИАМЕТРОМ ОТ 20 ДО 377 ММ ИЗ СТАЛИ МАРОК БСТ2КП-БСТ4КП И БСТ2ПС-БСТ4ПС НАРУЖНЫЙ ДИАМЕТР 325 ММ ТОЛЩИНА СТЕНКИ 6 ММ | D17: М | E17: 7.58 | F17: =+E17*$E$5 -> 7.58 | G17: =+VLOOKUP(C17&D17,Ресурсы!A:E,5,0) -> 519420 | H17: =+F17*G17 -> 3937203.6
... A26: 1.21 | B26: С 14370 | C26: ЩЕТКИ КОЛЬЦЕВЫЕ ПРОВОЛОЧНЫЕ | D26: ШТ | E26: 0.14 | F26: =+E26*$E$5 -> 0.14 | G26: =+VLOOKUP(C26&D26,Ресурсы!A:E,5,0) -> 35000 | H26: =+F26*G26 -> 4900
A27: РАЗДЕЛ 2. ОБОРУДОВАНИЕ, КАБЕЛЬ И МАТЕРИАЛЫ ЗАКАЗЧИКА
A28: 2 | B28: обор. | C28: КРАН ШАРОВОЙ ДУ500 РУ8,0 МПА ПОДЗЕМНОЙ УСТАНОВКИ | D28: ШТ | E28: Ф | F28: =Спецификация!D7 -> 3 | G28: =+VLOOKUP(C28&D28,Ресурсы!A:E,5,0) -> 185000000 | H28: =+F28*G28 -> 555000000 | I28: ⚠ Замечание № 1 к РД: спецификация 2 шт / лист ТХ-3 — 3 шт. Принято 3 шт
A29: 3 | B29: каб. | C29: КАБЕЛЬ ВВГНГ(А)-LS 3Х2,5 | D29: М | E29: Ф | F29: =Спецификация!D12 -> 150 | G29: =+VLOOKUP(C29&D29,Ресурсы!A:E,5,0) -> 12500 | H29: =+F29*G29 -> 1875000
A30: 4 | B30: мз | C30: ОТВОД ГНУТЫЙ 30° 530Х8 | D30: ШТ | E30: Ф | F30: =Спецификация!D9 -> 4 | G30: =+VLOOKUP(C30&D30,Ресурсы!A:E,5,0) -> 6800000 | H30: =+F30*G30 -> 27200000
B32: ВСЕГО ЗАТРАТ | D32: СУМ | H32: =SUM($H$5:$H$30) -> 6.6975574e+08
B33: Сзп | D33: СУМ | H33: =SUMIFS($H$5:$H$30,$D$5:$D$30,"ЧЕЛ-Ч") -> 4046400
B34: Сэм | D34: СУМ | H34: =SUMIFS($H$5:$H$30,$D$5:$D$30,"МАШ-Ч") -> 39683260
B35: Коэф. на стеснённые условия | D35: СУМ | F35: 0 | H35: =(H33+H34)*F35 -> 0
B36: См | D36: СУМ | H36: =H32-H33-H34-SUMIFS($H$5:$H$30,$B$5:$B$30,"обор.")-SUMIFS($H$5:$H$30,$B$5:$B$30,"каб.") -> 69151078
B37: Кабельная продукция | D37: СУМ | H37: =SUMIFS($H$5:$H$30,$B$5:$B$30,"каб.") -> 1875000
B38: Транспортные расходы на материалы | D38: СУМ | F38: 0.05 | H38: =H36*F38 -> 3457553.9
B39: Транспортные расходы на кабель | D39: СУМ | F39: 0.015 | H39: =H37*F39 -> 28125
B40: ЗСР | D40: СУМ | F40: 0.02 | H40: =H36*F40 -> 1383021.6
B41: ИТОГО | D41: СУМ | H41: =SUM(H33:H40) -> 1.1962444e+08
B42: ОБОРУДОВАНИЕ | D42: СУМ | H42: =SUMIFS($H$5:$H$30,$B$5:$B$30,"обор.") -> 555000000
B43: Транспортные расходы на оборудование | D43: СУМ | F43: 0.02 | H43: =H42*F43 -> 11100000
B44: Прочие затраты и расходы Подрядчика | D44: СУМ | F44: 0.17 | H44: =H41*F44 -> 20336154
B45: ИТОГО | D45: СУМ | H45: =SUM(H41:H44) -> 7.0606059e+08
B46: НДС | D46: СУМ | F46: 0.12 | H46: =H45*F46 -> 84727271
B47: МИНУС МАТЕРИАЛЫ ЗАКАЗЧИКА | D47: СУМ | H47: =-SUMIFS($H$5:$H$30,$B$5:$B$30,"мз") -> -27200000
B48: ВСЕГО СТОИМОСТЬ СТРОИТЕЛЬСТВА В ТЕКУЩИХ ЦЕНАХ (с НДС 12%) | D48: СУМ | H48: =H45+H46+H47 -> 7.6358786e+08

Sheet ЛРВ-ГП
A1: N п.п. | B1: Шифр номера нормативов и коды ресурсов | C1: Наименование работ и затрат | D1: Единица измерения | E1: Количество | G1: Стоимость | I1: Примечание
E2: на ед. изм. | F2: по проектным данным | G2: Стоимость за ед. | H2: СУММА
A3: 1 | B3: 2 | C3: 3 | D3: 4 | E3: 5 | F3: 6 | G3: 7 | H3: 8 | I3: 9
A4: РАЗДЕЛ 1. ЗЕМЛЯНЫЕ РАБОТЫ
A5: 1 | B5: 01-01-013-8 | C5: РАЗРАБОТКА ГРУНТА С ПОГРУЗКОЙ НА АВТОМОБИЛИ-САМОСВАЛЫ ЭКСКАВАТОРАМИ С КОВШОМ ВМЕСТИМОСТЬЮ 0,65 (0,5-1) М3, ГРУППА ГРУНТОВ 2 | D5: 1000 М3 | E5: =ВОР!D12/1000 -> 1.25
A6: 1.1 | B6: 1 | C6: ЗАТРАТЫ ТРУДА РАБОЧИХ-СТРОИТЕЛЕЙ | D6: ЧЕЛ-Ч | E6: 11.41 | F6: =+E6*$E$5 -> 14.2625 | G6: =+VLOOKUP(C6&D6,Ресурсы!A:E,5,0) -> 45000 | H6: =+F6*G6 -> 641812.5
A7: 1.2 | B7: 3 | C7: ЗАТРАТЫ ТРУДА МАШИНИСТОВ | D7: ЧЕЛ-Ч | E7: 33.09 | F7: =+E7*$E$5 -> 41.3625 | G7: =+VLOOKUP(C7&D7,Ресурсы!A:E,5,0) -> 0 | H7: =+F7*G7 -> 0
A8: 1.3 | B8: С2264 | C8: ЭКСКАВАТОРЫ ОДНОКОВШОВЫЕ ДИЗЕЛЬНЫЕ НА ГУСЕНИЧНОМ ХОДУ ПРИ РАБОТЕ НА ДРУГИХ ВИДАХ СТРОИТЕЛЬСТВА (КРОМЕ ВОДОХОЗЯЙСТВЕННОГО) 0,65 М3 | D8: МАШ-Ч | E8: 25.25 | F8: =+E8*$E$5 -> 31.5625 | G8: =+VLOOKUP(C8&D8,Ресурсы!A:E,5,0) -> 420000 | H8: =+F8*G8 -> 13256250
A9: 1.4 | B9: С258 | C9: БУЛЬДОЗЕРЫ ПРИ РАБОТЕ НА ДРУГИХ ВИДАХ СТРОИТЕЛЬСТВА (КРОМЕ ВОДОХОЗЯЙСТВЕННОГО) 79 (108) КВТ (Л.С.) | D9: МАШ-Ч | E9: 7.84 | F9: =+E9*$E$5 -> 9.8 | G9: =+VLOOKUP(C9&D9,Ресурсы!A:E,5,0) -> 380000 | H9: =+F9*G9 -> 3724000
A10: 1.5 | B10: М43113 | C10: ЩЕБЕНЬ | D10: М3 | E10: 0.04 | F10: =+E10*$E$5 -> 0.05 | G10: =+VLOOKUP(C10&D10,Ресурсы!A:E,5,0) -> 203000 | H10: =+F10*G10 -> 10150
B12: ВСЕГО ЗАТРАТ | D12: СУМ | H12: =SUM($H$5:$H$10) -> 17632212
B13: Сзп | D13: СУМ | H13: =SUMIFS($H$5:$H$10,$D$5:$D$10,"ЧЕЛ-Ч") -> 641812.5
B14: Сэм | D14: СУМ | H14: =SUMIFS($H$5:$H$10,$D$5:$D$10,"МАШ-Ч") -> 16980250
B15: Коэф. на стеснённые условия | D15: СУМ | F15: 0 | H15: =(H13+H14)*F15 -> 0
B16: См | D16: СУМ | H16: =H12-H13-H14-SUMIFS($H$5:$H$10,$B$5:$B$10,"обор.")-SUMIFS($H$5:$H$10,$B$5:$B$10,"каб.") -> 10150
B17: Кабельная продукция | D17: СУМ | H17: =SUMIFS($H$5:$H$10,$B$5:$B$10,"каб.") -> 0
B18: Транспортные расходы на материалы | D18: СУМ | F18: 0.05 | H18: =H16*F18 -> 507.5
B19: Транспортные расходы на кабель | D19: СУМ | F19: 0.015 | H19: =H17*F19 -> 0
B20: ЗСР | D20: СУМ | F20: 0.02 | H20: =H16*F20 -> 203
B21: ИТОГО | D21: СУМ | H21: =SUM(H13:H20) -> 17632923
B22: ОБОРУДОВАНИЕ | D22: СУМ | H22: =SUMIFS($H$5:$H$10,$B$5:$B$10,"обор.") -> 0
B23: Транспортные расходы на оборудование | D23: СУМ | F23: 0.02 | H23: =H22*F23 -> 0
B24: Прочие затраты и расходы Подрядчика | D24: СУМ | F24: 0.17 | H24: =H21*F24 -> 2997596.9
B25: ИТОГО | D25: СУМ | H25: =SUM(H21:H24) -> 20630520
B26: НДС | D26: СУМ | F26: 0.12 | H26: =H25*F26 -> 2475662.4
B27: МИНУС МАТЕРИАЛЫ ЗАКАЗЧИКА | D27: СУМ | H27: =-SUMIFS($H$5:$H$10,$B$5:$B$10,"мз") -> 0
B28: ВСЕГО СТОИМОСТЬ СТРОИТЕЛЬСТВА В ТЕКУЩИХ ЦЕНАХ (с НДС 12%) | D28: СУМ | H28: =H25+H26+H27 -> 23106182
